ons/__init__.py
ons-0.2.2.dist-info/entry_points.txt
ons-0.2.2.dist-info/LICENSE
ons-0.2.2.dist-info/WHEEL
ons-0.2.2.dist-info/METADATA
ons-0.2.2.dist-info/RECORD
