Metadata-Version: 2.1
Name: ons
Version: 0.2.2
Summary: ons 
Author-email: DK <tk@terminalkitten.com>
Classifier: License :: OSI Approved :: MIT License
Requires-Dist: typing-extensions
Requires-Dist: pydantic
Requires-Dist: click
Requires-Dist: httpx
Requires-Dist: uvicorn[standard]
Requires-Dist: devtools
Requires-Dist: pyfiglet
Requires-Dist: wasabi
Requires-Dist: black ; extra == "dev"
Requires-Dist: ipdb ; extra == "dev"
Requires-Dist: ipython ; extra == "dev"
Requires-Dist: flit ; extra == "dev"
Requires-Dist: flake8 ; extra == "dev"
Requires-Dist: pytest ; extra == "dev"
Requires-Dist: mypy ; extra == "dev"
Requires-Dist: isort ; extra == "dev"
Requires-Dist: wheel ; extra == "dev"
Requires-Dist: pdoc3 ; extra == "doc"
Project-URL: Home, https://github.com/terminalkitten/ons
Provides-Extra: dev
Provides-Extra: doc
